Metadata-Version: 2.1
Name: codul-meu
Version: 0.0.1
Summary: Tulai da mult ii die lucru la pachetele aiestea, eu cred ca fac tendonita de la atata lucru
Author: Bogdan Chisu
Author-email: bchisu@gmail.com
License-File: LICENSE
